.installed.cfg
CHANGES.rst
CREDITS.rst
MANIFEST.in
README.rst
buildout.cfg
setup.cfg
setup.py
betahaus/__init__.py
betahaus.viewcomponent.egg-info/PKG-INFO
betahaus.viewcomponent.egg-info/SOURCES.txt
betahaus.viewcomponent.egg-info/dependency_links.txt
betahaus.viewcomponent.egg-info/entry_points.txt
betahaus.viewcomponent.egg-info/not-zip-safe
betahaus.viewcomponent.egg-info/requires.txt
betahaus.viewcomponent.egg-info/top_level.txt
betahaus/viewcomponent/__init__.py
betahaus/viewcomponent/compat.py
betahaus/viewcomponent/decorators.py
betahaus/viewcomponent/interfaces.py
betahaus/viewcomponent/models.py
betahaus/viewcomponent/tests.py
betahaus/viewcomponent/fixtures/__init__.py
betahaus/viewcomponent/fixtures/contexts.py
betahaus/viewcomponent/fixtures/dummy.py
betahaus/viewcomponent/fixtures/group.py