Metadata-Version: 1.0
Name: betahaus.viewcomponent
Version: 0.4.1
Summary: Plugin structure for menus, JSON responses or similar.
Home-page: https://github.com/robinharms/betahaus.viewcomponent
Author: Robin Harms Oredsson
Author-email: robin@betahaus.net
License: UNKNOWN
Keywords: web pyramid pylons
Platform: UNKNOWN
Classifier: Development Status :: 5 - Production/Stable
Classifier: Environment :: Web Environment
Classifier: Framework :: Pyramid
Classifier: Intended Audience :: Developers
Classifier: License :: OSI Approved :: GNU General Public License v3 (GPLv3)
Classifier: Programming Language :: Python :: 2.6
Classifier: Programming Language :: Python :: 2.7
Classifier: Programming Language :: Python :: 3
Classifier: Programming Language :: Python
Classifier: Topic :: Internet :: WWW/HTTP :: Dynamic Content
Classifier: Topic :: Internet :: WWW/HTTP
